ckanext/__init__.py
ckanext/conftest.py
ckanext/datapackage/__init__.py
ckanext/datapackage/actions.py
ckanext/datapackage/auth.py
ckanext/datapackage/blueprint.py
ckanext/datapackage/plugin.py
ckanext/datapackage/settings.py
ckanext/datapackage/__spec__/test_placeholder.py
ckanext/datapackage/templates/package/snippets/additional_info.html
ckanext_datapackage-0.2.4.dist-info/METADATA
ckanext_datapackage-0.2.4.dist-info/WHEEL
ckanext_datapackage-0.2.4.dist-info/entry_points.txt
ckanext_datapackage-0.2.4.dist-info/licenses/LICENSE.md
ckanext_datapackage-0.2.4.dist-info/RECORD
