Metadata-Version: 2.3
Name: ckanext-datapackage
Version: 0.2.4
Summary: Data Package integreation for CKAN
Project-URL: homepage, https://github.com/frictionlessdata/ckanext-datapackage
Author-email: Open Knowledge Foundation <info@okfn.org>
License-Expression: MIT
License-File: LICENSE.md
Keywords: data package,data validation,json schema,json table schema,open data,tabular data package
Classifier: Development Status :: 4 - Beta
Classifier: Environment :: Console
Classifier: Intended Audience :: Developers
Classifier: License :: OSI Approved :: MIT License
Classifier: Operating System :: OS Independent
Classifier: Programming Language :: Python :: 3
Classifier: Programming Language :: Python :: 3.8
Classifier: Programming Language :: Python :: 3.9
Classifier: Programming Language :: Python :: 3.10
Classifier: Programming Language :: Python :: 3.11
Classifier: Programming Language :: Python :: 3.12
Classifier: Topic :: Software Development :: Libraries :: Python Modules
Requires-Python: >=3.8
Requires-Dist: dplib-py==0.7.9
Provides-Extra: dev
Requires-Dist: ckan; extra == 'dev'
Requires-Dist: flask; extra == 'dev'
Requires-Dist: hatch; extra == 'dev'
Requires-Dist: ipython; extra == 'dev'
Requires-Dist: neovim; extra == 'dev'
Requires-Dist: pyright; extra == 'dev'
Requires-Dist: pytest; extra == 'dev'
Requires-Dist: pytest-cov; extra == 'dev'
Requires-Dist: pytest-dotenv; extra == 'dev'
Requires-Dist: pytest-lazy-fixtures; extra == 'dev'
Requires-Dist: pytest-mock; extra == 'dev'
Requires-Dist: pytest-timeout; extra == 'dev'
Requires-Dist: pytest-vcr; extra == 'dev'
Requires-Dist: ruff; extra == 'dev'
